{"builder":{"builderType":"uri","providerClassName":"qupath.lib.images.servers.bioformats.BioFormatsServerBuilder","uri":"file://forskning.it.ntnu.no/ntnu/mh-kin/moser/kobro/Students/Raissa%20Lejneva/18%20months/26142(-)sap/26142_5.czi","args":["--series","0"],"metadata":{"name":"26142_5.czi - Scene #01","width":23189,"height":38938,"sizeZ":1,"sizeT":1,"channelType":"DEFAULT","isRGB":true,"pixelType":"UINT8","levels":[{"downsample":1.0,"width":23189,"height":38938},{"downsample":2.0,"width":11594,"height":19469},{"downsample":4.0,"width":5797,"height":9734},{"downsample":8.0,"width":2898,"height":4867},{"downsample":16.0,"width":1449,"height":2433},{"downsample":32.0,"width":724,"height":1216},{"downsample":64.0,"width":362,"height":608}],"channels":[{"name":"Red","color":-65536},{"name":"Green","color":-16711936},{"name":"Blue","color":-16776961}],"pixelCalibration":{"pixelWidth":{"value":0.21971294503730876,"unit":"µm"},"pixelHeight":{"value":0.21971294503730876,"unit":"µm"},"zSpacing":{"value":1.0,"unit":"z-slice"},"timeUnit":"SECONDS","timepoints":[]},"magnification":20.0,"preferredTileWidth":1024,"preferredTileHeight":1024}},"metadata":{"name":"26142_5.czi - Scene #01","width":23189,"height":38938,"sizeZ":1,"sizeT":1,"channelType":"DEFAULT","isRGB":true,"pixelType":"UINT8","levels":[{"downsample":1.0,"width":23189,"height":38938},{"downsample":2.0,"width":11594,"height":19469},{"downsample":4.0,"width":5797,"height":9734},{"downsample":8.0,"width":2898,"height":4867},{"downsample":16.0,"width":1449,"height":2433},{"downsample":32.0,"width":724,"height":1216},{"downsample":64.0,"width":362,"height":608}],"channels":[{"name":"Red","color":-65536},{"name":"Green","color":-16711936},{"name":"Blue","color":-16776961}],"pixelCalibration":{"pixelWidth":{"value":0.21971294503730876,"unit":"µm"},"pixelHeight":{"value":0.21971294503730876,"unit":"µm"},"zSpacing":{"value":1.0,"unit":"z-slice"},"timeUnit":"SECONDS","timepoints":[]},"magnification":20.0,"preferredTileWidth":1024,"preferredTileHeight":1024}}